virtuoso/COUNTER/counter/functional/verilog.v
// Created by ihdl
module  counter(
output [7:0] out,
input enable,
input clk,
input reset
);

reg [7:0] out;

always @(posedge clk)
begin
    if (reset) begin
        out <= 8'b0;
    end else if (enable) begin
        out <= out + 1;
    end
end

endmodule

src/counter_tb.v
`timescale 1ns/10ps

//`include "counter.v"

module counter_tb;

reg clk, reset, enable;
wire [7:0] out;

initial begin
	$dumpfile("dump.vcd");
	$dumpvars(0,counter1);
	clk = 0;
	reset = 0;
	enable = 0;
	#24 reset = 1;
	#20 reset = 0;
	#20 enable = 1;	
	#500 $finish;
end

always begin
	#10 clk = ~clk;
end

counter counter1(out,enable,clk,reset);

endmodule //test

sim_rtl/dump.vcd
$date
    Nov 22, 2021  11:42:11
$end
$version
    TOOL:	xmsim(64)	18.03-s018
$end
$timescale
    1 ps
$end

$scope module counter_tb $end

$scope module counter1 $end
$var reg       8 !    out [7:0] $end
$var wire      1 "    enable  $end
$var wire      1 #    clk  $end
$var wire      1 $    reset  $end
$upscope $end

$upscope $end

$enddefinitions $end
$dumpvars
bx !
0"
0#
0$
$end
#10000
1#
#20000
0#
#24000
1$
#30000
1#
b0 !
#40000
0#
#44000
0$
#50000
1#
#60000
0#
#64000
1"
#70000
1#
b1 !
#80000
0#
#90000
1#
b10 !
#100000
0#
#110000
1#
b11 !
#120000
0#
#130000
1#
b100 !
#140000
0#
#150000
1#
b101 !
#160000
0#
#170000
1#
b110 !
#180000
0#
#190000
1#
b111 !
#200000
0#
#210000
1#
b1000 !
#220000
0#
#230000
1#
b1001 !
#240000
0#
#250000
1#
b1010 !
#260000
0#
#270000
1#
b1011 !
#280000
0#
#290000
1#
b1100 !
#300000
0#
#310000
1#
b1101 !
#320000
0#
#330000
1#
b1110 !
#340000
0#
#350000
1#
b1111 !
#360000
0#
#370000
1#
b10000 !
#380000
0#
#390000
1#
b10001 !
#400000
0#
#410000
1#
b10010 !
#420000
0#
#430000
1#
b10011 !
#440000
0#
#450000
1#
b10100 !
#460000
0#
#470000
1#
b10101 !
#480000
0#
#490000
1#
b10110 !
#500000
0#
#510000
1#
b10111 !
#520000
0#
#530000
1#
b11000 !
#540000
0#
#550000
1#
b11001 !
